coco_froc_analysis/__init__.py
coco_froc_analysis/__main__.py
coco_froc_analysis/cli_froc_analysis.py
coco_froc_analysis/count/__init__.py
coco_froc_analysis/count/bootstrap_count_curve.py
coco_froc_analysis/count/count_curve.py
coco_froc_analysis/count/count_stats.py
coco_froc_analysis/froc/__init__.py
coco_froc_analysis/froc/bootstrap_froc_curve.py
coco_froc_analysis/froc/froc_curve.py
coco_froc_analysis/froc/froc_stats.py
coco_froc_analysis/utils.py
coco_froc_analysis-0.2.15.dist-info/LICENSE
coco_froc_analysis-0.2.15.dist-info/METADATA
coco_froc_analysis-0.2.15.dist-info/WHEEL
coco_froc_analysis-0.2.15.dist-info/RECORD
