Metadata-Version: 2.1
Name: coco-froc-analysis
Version: 0.2.15
Summary: FROC analysis for COCO detections for Detectron(2) and OpenMMLab
License: MIT
Author: Alex Olar
Author-email: olaralex666@gmail.com
Requires-Python: >=3.9.18,<4.0.0
Classifier: License :: OSI Approved :: MIT License
Classifier: Programming Language :: Python :: 3
Classifier: Programming Language :: Python :: 3.10
Classifier: Programming Language :: Python :: 3.11
Classifier: Programming Language :: Python :: 3.12
Requires-Dist: flake8 (>=7.0.0,<8.0.0)
Requires-Dist: matplotlib (>=3.6.2,<4.0.0)
Requires-Dist: numpy (>=1.23.5,<2.0.0)
Requires-Dist: scipy (>=1.9.3,<2.0.0)
Requires-Dist: tqdm (>=4.64.1,<5.0.0)
